{"content-type":"\"text/html; charset=UTF-8","content-security-policy-report-only":"\"object-src 'none';base-uri 'self';script-src 'nonce-RwGkuPLV4Yz90f7T2LSoPw' 'strict-dynamic' 'report-sample' 'unsafe-eval' 'unsafe-inline' https: http:;report-uri https://csp.withgoogle.com/csp/gws/other-hp","content-encoding":"\"gzip","date":"\"Sat, 06 May 2023 12:38:30 GMT","cache-control":"\"private","content-length":"\"67120","x-xss-protection":"\"0","x-frame-options":"\"SAMEORIGIN","expires":"\"Sat, 06 May 2023 12:38:30 GMT","set-cookie":"\"AEC=AUEFqZe2uxssqMQD1WvhnNvnmkpf6mJSH4mhmzaEe1NGck1U8lIqVis11CI; expires=Thu, 02-Nov-2023 12:38:30 GMT; path=/; domain=.google.com; Secure; HttpOnly; SameSite=lax\\n__Secure-ENID=12.SE=HDDWZghcyAgZpnTemmJap8aozHsC1WuytzpRNLjMxyPVT2jPcXgZRbu1eAZfVsNiYg0GN9OFUr1T2WOiFKU3JXbFfwZhN6ANPS6S82qzj7uIW_k5L7AsqFYjBiIwOoCiXPbh1-MYs8htsaXZgLdNP7r2r6rAbSvJUJNe4_3lM9E; expires=Wed, 05-Jun-2024 04:56:48 GMT; path=/; domain=.google.com; Secure; HttpOnly; SameSite=lax\\nCONSENT=PENDING+081; expires=Mon, 05-May-2025 12:38:30 GMT; path=/; domain=.google.com; Secure","strict-transport-security":"\"max-age=31536000","p3p":"\"CP=\\\"This is not a P3P policy! See g.co/p3phelp for more info.\\\"","server":"\"gws","alt-svc":"\"h3=\\\":443\\\"; ma=2592000, h3-29=\\\":443\\\"; ma=2592000","url":"https://www.google.com"}