{"Total devices":[],"Homepage with safe csp":false,"Homepage with safe csp using following devices":[],"Homepage with not safe csp using following devices":[],"Subpages with safe csp":"0 are with safe csp","Subpages with not safe csp":"5 are with not safe csp","Subpages with safe csp using following devices":[],"Subpages with not safe csp using following devices":[],"Homepage with csp header":false,"Homepage with csp header using following devices":[],"Homepage without csp header using following devices":[],"Subpages with csp header":0,"Subpages without csp header":5,"Subpages with csp header using following devices":[],"Subpages without csp header using following devices":[]}